Workbook

Sheet Raw Data
A1: Metric | B1: FY21 | C1: FY22 | D1: FY23 | E1: FY24 | F1: FY25 | G1: FY26 | J1: Notes / Sources
A2: Sales | B2: 152 | C2: 199 | D2: 202 | E2: 272 | F2: 417 | G2: 388 | H2: =SUM(B2:G2) -> 1630 | J2: All figures in Rs Crore, consolidated. Source: Screener.in - Premier Explosives Ltd, Profit & Loss / Balance Sheet tabs.
A3: EBITDA | B3: 7 | C3: 21 | D3: 26 | E3: 58 | F3: 58 | G3: 39 | H3: =SUM(B3:G3) -> 209
A4: Net Profit | B4: -11 | C4: 5 | D4: 7 | E4: 28 | F4: 29 | G4: 46 | H4: =SUM(B4:G4) -> 104
A5: Debt | B5: 58 | C5: 78 | D5: 83 | E5: 61 | F5: 41 | G5: 32 | J5: Total debt, FY26 (latest reported year).
A6: Cash | B6: 6 | C6: 5 | D6: 7 | E6: 29 | F6: 101 | G6: 60 | J6: Cash & equivalents, FY26 (latest reported year).
A7: Market Cap | G7: 3858 | J7: DUE DILIGENCE FLAG: EBITDA fell from 58 (FY25) to 39 (FY26) even though Sales was roughly flat (417 to 388) - margin compression in the latest year. See memo.

Sheet Ratios
A1: Metric | B1: Value
A2: Sales CAGR | B2: =(('Raw Data'!G2/'Raw Data'!B2)^(1/5))-1 -> 0.20613974
A3: Avg EBITDA Margin | B3: =AVERAGE('Raw Data'!H3/'Raw Data'!H2) -> 0.12822086
A4: Avg Net Margin | B4: =AVERAGE('Raw Data'!H4/'Raw Data'!H2) -> 0.063803681

Sheet DCF
A1: Metric | B1: Year 1 | C1: Year 2 | D1: Year 3 | E1: Year 4 | F1: Year 5
A2: Revenue | B2: ='Raw Data'!G2*(1+Ratios!B2) -> 467.98222 | C2: =B2*(1+Ratios!B2) -> 564.45195 | D2: =C2*(1+Ratios!B2) -> 680.80793 | E2: =D2*(1+Ratios!B2) -> 821.14951 | F2: =E2*(1+Ratios!B2) -> 990.42105
A3: EBITDA | B3: =B2*Ratios!B3 -> 60.005082 | C3: =C2*Ratios!B3 -> 72.374514 | D3: =D2*Ratios!B3 -> 87.293778 | E3: =E2*Ratios!B3 -> 105.28849 | F3: =F2*Ratios!B3 -> 126.99264
A4: Free Cash Flow | B4: =B3*0.7 -> 42.003558 | C4: =C3*0.7 -> 50.66216 | D4: =D3*0.7 -> 61.105645 | E4: =E3*0.7 -> 73.701946 | F4: =F3*0.7 -> 88.894847
A5: Discount Factor | B5: =1/(1.13)^1 -> 0.88495575 | C5: =1/(1.13)^2 -> 0.78314668 | D5: =1/(1.13)^3 -> 0.69305016 | E5: =1/(1.13)^4 -> 0.61331873 | F5: =1/(1.13)^5 -> 0.54275994
A6: Present Value (PV) of FCF | B6: =B4*B5 -> 37.17129 | C6: =C4*C5 -> 39.675903 | D6: =D4*D5 -> 42.349277 | E6: =E4*E5 -> 45.202784 | F6: =F4*F5 -> 48.248561 | G6: =SUM(B6:F6) -> 212.64781
A8: Terminal Value | B8: =(F4*1.05)/(0.13-0.05) -> 1166.7449 | C8: (Gordon Growth: FCF Year 5 x (1+terminal growth) / (discount rate - terminal growth). Terminal growth = 5%, discount rate = 13%.)
A9: PV of Terminal Value | B9: =B8*F5 -> 633.26237
A10: Enterprise Value | B10: =SUM(B6:F6)+B9 -> 845.91018
A11: Equity Value (EV - Debt + Cash, FY26) | B11: =B10-'Raw Data'!G5+'Raw Data'!G6 -> 873.91018
A12: Key assumptions
A13: Discount rate (WACC proxy) | B13: 0.13 | C13: Standard cost of capital for an Indian small/mid-cap; higher than a diagnostics/consumer business given defence-manufacturing regulatory and execution risk.
A14: Terminal growth rate | B14: 0.05 | C14: Proxy for long-run nominal GDP growth.
A16: Implied EV/EBITDA multiple (DCF-derived) | B16: =B10/B3 -> 14.097309
A17: Cross-check: multiple x Latest Actual EBITDA (FY26) | B17: =B16*'Raw Data'!G3 -> 549.79505

Sheet Comps
A1: Company | B1: Market Cap | C1: Debt | D1: Cash | E1: EBITDA | F1: EV | G1: EV/EBITDA
A2: GOCL Corp (EXCLUDED - see note) | B2: 1822 | C2: 1013 | D2: 894 | E2: N/M | I2: Excluded: GOCL's FY26 operating business posted a NEGATIVE operating profit (core explosives/detonator business shrank sharply after discontinuing part of that business); its reported net profit is dominated by a one-off ~Rs 1,671 Cr other-income / asset-discontinuation gain, not recurring operations. An EV/EBITDA multiple built on that is not comparable to Premier's core operating business. Source: Screener.in, MarketsMojo quarterly result analysis, accessed July 2026.
A3: Astra Microwave | B3: 17144 | C3: 1988 | D3: 253 | E3: 334 | F3: =B3+C3-D3 -> 18879 | G3: =F3/E3 -> 56.523952 | I3: Source: Screener.in, accessed July 2026 (Market Cap Rs 17,144 Cr).
A4: Solar Industries | B4: 157272 | C4: 1468 | D4: 601 | E4: 2750 | F4: =B4+C4-D4 -> 158139 | G4: =F4/E4 -> 57.505091 | I4: Source: Screener.in + Solar Industries FY26 results (EBITDA Rs 2,750 Cr, FY26). Added as a second, larger, pure-play explosives/defence peer since GOCL is not comparable this year.
A5: Average (Astra + Solar only) | G5: =AVERAGE(G3:G4) -> 57.014522
A7: Premier EBITDA - FY26 (latest, post margin-compression) | B7: ='Raw Data'!G3 -> 39
A8: Premier EBITDA - FY25 (prior peak year) | B8: ='Raw Data'!F3 -> 58
A9: Peer average EV/EBITDA applied | B9: =G5 -> 57.014522
A10: Implied EV using FY26 EBITDA | B10: =B7*B9 -> 2223.5663
A11: Implied EV using FY25 EBITDA | B11: =B8*B9 -> 3306.8422
A12: Implied Equity Value (FY26 EBITDA basis): EV - Debt + Cash | B12: =B10-'Raw Data'!G5+'Raw Data'!G6 -> 2251.5663
A13: Implied Equity Value (FY25 EBITDA basis): EV - Debt + Cash | B13: =B11-'Raw Data'!G5+'Raw Data'!G6 -> 3334.8422

Sheet Summary
A1: Premier Explosives - Independent Valuation vs. Actual Deal Price
A2: Apollo Micro Systems acquisition of 41.33% promoter stake, announced 9 July 2026
A4: Method | B4: Enterprise Value (Rs Cr) | C4: Equity Value (Rs Cr) | D4: Basis / Note
A5: DCF (5-yr, 13% discount rate) | B5: =DCF!B10 -> 845.91018 | C5: =DCF!B11 -> 873.91018 | D5: Simplified single-growth-rate DCF; most conservative estimate.
A6: Comps - FY26 EBITDA (declined yr) | B6: =Comps!B10 -> 2223.5663 | C6: =Comps!B12 -> 2251.5663 | D6: Applies Astra/Solar avg multiple to Premier's latest (weaker) FY26 EBITDA of 39 Cr.
A7: Comps - FY25 EBITDA (peak yr) | B7: =Comps!B11 -> 3306.8422 | C7: =Comps!B13 -> 3334.8422 | D7: Same multiple applied to FY25 EBITDA of 58 Cr - shows sensitivity to which year is used.
A8: Current Market Cap (reference) | C8: ='Raw Data'!G7 -> 3858 | D8: Screener.in, accessed July 2026 - not a valuation method, shown for reference.
A10: ACTUAL DEAL (real, disclosed)
A11: Deal price for 41.33% stake | B11: 1550 | D11: All-cash, Share Purchase Agreement signed 9 July 2026 (Business Standard, TipRanks).
A12: Implied 100% equity value | C12: =1550/0.4133 -> 3750.3024 | D12: Rs 1,550 Cr / 41.33% stake sold. This is the number to compare your DCF/Comps equity values against.
A14: Reading the table
A15: 1. Your DCF (~Rs 875 Cr equity value, using the corrected terminal value formula) sits well below the deal's implied Rs 3,750 Cr equity value. This is expected from a simplified, conservative single-growth-rate model - not an error.
A16: 2. The comps method using FY25 (peak) EBITDA lands closest to both the market cap and the actual deal value, while FY26 (declined) EBITDA gives a much lower number - the choice of EBITDA year materially changes the answer, which is worth flagging explicitly rather than picking whichever looks nicer.
A17: 3. The deal's implied equity value (~Rs 3,750 Cr) is close to Premier's prevailing market cap (~Rs 3,858 Cr) - Apollo does not appear to be paying a large premium over the public market price for this controlling stake, which is itself a notable finding worth stating in the memo.
A18: 4. Do not adjust your DCF or comps assumptions backward to force them closer to the deal price - the gap and its explanation is the actual analytical output here.
